{
  "id": "",
  "name": "",
  "font_family": "iconfont",
  "css_prefix_text": "icon-",
  "description": "",
  "glyphs": [
    {
      "icon_id": "288646",
      "name": "menu",
      "font_class": "menu",
      "unicode": "e672",
      "unicode_decimal": 58994
    },
    {
      "icon_id": "1315584",
      "name": "电影院",
      "font_class": "dianyingyuan",
      "unicode": "e602",
      "unicode_decimal": 58882
    },
    {
      "icon_id": "2675007",
      "name": "我的",
      "font_class": "wode",
      "unicode": "e62f",
      "unicode_decimal": 58927
    },
    {
      "icon_id": "5008614",
      "name": "放大镜",
      "font_class": "icon-test",
      "unicode": "e603",
      "unicode_decimal": 58883
    },
    {
      "icon_id": "5037718",
      "name": "左箭头",
      "font_class": "zuojiantou",
      "unicode": "e629",
      "unicode_decimal": 58921
    },
    {
      "icon_id": "7148955",
      "name": "右箭头",
      "font_class": "youjiantou",
      "unicode": "e61c",
      "unicode_decimal": 58908
    },
    {
      "icon_id": "11372657",
      "name": "电影票",
      "font_class": "dianyingpiao",
      "unicode": "e8ae",
      "unicode_decimal": 59566
    },
    {
      "icon_id": "14560712",
      "name": "视频",
      "font_class": "shipin",
      "unicode": "e62a",
      "unicode_decimal": 58922
    },
    {
      "icon_id": "15682555",
      "name": "视频",
      "font_class": "shipin1",
      "unicode": "e608",
      "unicode_decimal": 58888
    }
  ]
}
